mysensors/VERSION
mysensors/__init__.py
mysensors/const.py
mysensors/const_14.py
mysensors/const_15.py
mysensors/const_20.py
mysensors/const_21.py
mysensors/const_22.py
mysensors/gateway_mqtt.py
mysensors/gateway_serial.py
mysensors/gateway_tcp.py
mysensors/handler.py
mysensors/message.py
mysensors/mysensors.py
mysensors/ota.py
mysensors/persistence.py
mysensors/sensor.py
mysensors/task.py
mysensors/transport.py
mysensors/util.py
mysensors/validation.py
mysensors/cli/__init__.py
mysensors/cli/gateway_mqtt.py
mysensors/cli/gateway_serial.py
mysensors/cli/gateway_tcp.py
mysensors/cli/helper.py
pymysensorsrma-0.22.0.dist-info/LICENSE
pymysensorsrma-0.22.0.dist-info/METADATA
pymysensorsrma-0.22.0.dist-info/WHEEL
pymysensorsrma-0.22.0.dist-info/entry_points.txt
pymysensorsrma-0.22.0.dist-info/top_level.txt
pymysensorsrma-0.22.0.dist-info/zip-safe
pymysensorsrma-0.22.0.dist-info/RECORD
