Metadata-Version: 2.1
Name: pymysensorsrma
Version: 0.22.0
Summary: Python API for talking to a MySensors gateway
Home-page: https://github.com/theolind/pymysensors
Author: Theodor Lindquist
Author-email: theodor.lindquist@gmail.com
License: MIT License
Keywords: sensor,actuator,IoT,DYI
Platform: UNKNOWN
Classifier: Intended Audience :: Developers
Classifier: Intended Audience :: End Users/Desktop
Classifier: License :: OSI Approved :: MIT License
Classifier: Natural Language :: English
Classifier: Operating System :: OS Independent
Classifier: Programming Language :: Python :: 3.6
Classifier: Programming Language :: Python :: 3.7
Classifier: Programming Language :: Python :: 3.8
Classifier: Programming Language :: Python :: 3.9
Classifier: Topic :: Home Automation
Requires-Python: >=3.6
Requires-Dist: click
Requires-Dist: crcmod (>=1.7)
Requires-Dist: getmac
Requires-Dist: IntelHex (>=2.2.1)
Requires-Dist: pyserial (>=3.4)
Requires-Dist: pyserial-asyncio (>=0.4)
Requires-Dist: voluptuous (>=0.11.1)
Provides-Extra: mqtt-client
Requires-Dist: paho-mqtt ; extra == 'mqtt-client'
